README.rst
setup.py
m9dicts/__init__.py
m9dicts/api.py
m9dicts/compat.py
m9dicts/dicts.py
m9dicts/globals.py
m9dicts/relations.py
m9dicts/utils.py
m9dicts.egg-info/PKG-INFO
m9dicts.egg-info/SOURCES.txt
m9dicts.egg-info/dependency_links.txt
m9dicts.egg-info/top_level.txt
m9dicts/tests/__init__.py
m9dicts/tests/api.py
m9dicts/tests/common.py
m9dicts/tests/dicts.py
m9dicts/tests/relations.py
m9dicts/tests/utils.py